unscii/__init__.py
unscii/unscii.py
unscii/raw_unscii/__init__.py
unscii/raw_unscii/unscii_16.py
unscii/raw_unscii/unscii_16_transposed.py
unscii/raw_unscii/unscii_8.py
unscii/raw_unscii/unscii_8_alt.py
unscii/raw_unscii/unscii_8_alt_transposed.py
unscii/raw_unscii/unscii_8_fantasy.py
unscii/raw_unscii/unscii_8_fantasy_transposed.py
unscii/raw_unscii/unscii_8_mcr.py
unscii/raw_unscii/unscii_8_mcr_transposed.py
unscii/raw_unscii/unscii_8_tall.py
unscii/raw_unscii/unscii_8_tall_transposed.py
unscii/raw_unscii/unscii_8_thin.py
unscii/raw_unscii/unscii_8_thin_transposed.py
unscii/raw_unscii/unscii_8_transposed.py
unscii-0.1.1.dist-info/LICENSE
unscii-0.1.1.dist-info/METADATA
unscii-0.1.1.dist-info/WHEEL
unscii-0.1.1.dist-info/top_level.txt
unscii-0.1.1.dist-info/RECORD
