Metadata-Version: 2.1
Name: unscii
Version: 0.1.1
Summary: Python Interface for UNSCII bitmapped fonts
Home-page: https://github.com/grant-olson/py-unscii
Author: Grant T. Olson
Author-email: kgo@grant-olson.net
License: UNKNOWN
Platform: UNKNOWN
Classifier: License :: OSI Approved :: BSD License
Classifier: Programming Language :: Python :: 2
Classifier: Programming Language :: Python :: 3
Classifier: Operating System :: OS Independent
